ectf/__init__.py
ectf/cli.py
ectf/console.py
ectf/api/__init__.py
ectf/api/api_interface.py
ectf/api/cli.py
ectf/api/flow.py
ectf/hw/__init__.py
ectf/hw/bootloader.py
ectf/hw/cli.py
ectf/hw/fthr.py
ectf/hw/ti/__init__.py
ectf/hw/ti/protocol.py
ectf/tools/__init__.py
ectf/tools/cli.py
ectf/tools/hsm_interface.py
ectf-2026.0.1.dist-info/METADATA
ectf-2026.0.1.dist-info/WHEEL
ectf-2026.0.1.dist-info/entry_points.txt
ectf-2026.0.1.dist-info/licenses/LICENSE.txt
ectf-2026.0.1.dist-info/RECORD
